simulateSource/BLETransmissionConstant.py
simulateSource/ExitThreadMsg.py
simulateSource/Packet.py
simulateSource/ParseBLEPacket.py
simulateSource/ParsePacket.py
simulateSource/SerialCommunication.py
simulateSource/SimulateBehaviour.py
simulateSource/SimulateParams.py
simulateSource/SimulateSource.py
simulateSource/SingleSimulateParams.py
simulateSource/TraceSimulateParams.py
simulateSource/TransmissionConstant.py
simulateSource/__init__.py
simulateSource-1.1.2.dist-info/METADATA
simulateSource-1.1.2.dist-info/WHEEL
simulateSource-1.1.2.dist-info/top_level.txt
simulateSource-1.1.2.dist-info/RECORD
