Metadata-Version: 2.1
Name: simulateSource
Version: 1.1.2
Summary: 模拟源控制
Home-page: UNKNOWN
Author: wscec
Author-email: 
License: UNKNOWN
Platform: UNKNOWN
